lrc_adjuster/__init__.py
lrc_adjuster/adjuster.py
lrc_adjuster-0.1.2.dist-info/LICENSE
lrc_adjuster-0.1.2.dist-info/METADATA
lrc_adjuster-0.1.2.dist-info/WHEEL
lrc_adjuster-0.1.2.dist-info/entry_points.txt
lrc_adjuster-0.1.2.dist-info/RECORD
